README.rst
setup.py
offlinetb/__init__.py
offlinetb/__version__.py
offlinetb.egg-info/PKG-INFO
offlinetb.egg-info/SOURCES.txt
offlinetb.egg-info/dependency_links.txt
offlinetb.egg-info/namespace_packages.txt
offlinetb.egg-info/top_level.txt