Metadata-Version: 1.1
Name: offlinetb
Version: 0.0.6
Summary: Tools for distilling tracebacks for offline viewing
Home-page: http://github.com/vmalloc/offlinetb
Author: Rotem Yaari
Author-email: vmalloc@gmail.com
License: BSD
Platform: UNKNOWN
Classifier: Programming Language :: Python :: 2.7
